[
  {
    "id": 1,
    "product_size_id": 1,
    "layout_id": 1,
    "set_id": 1,
    "image_filename": "product_sizes_layouts_sets/1_v3.png",
    "is_listed": 1
  },
  {
    "id": 3,
    "product_size_id": 1,
    "layout_id": 1,
    "set_id": 3,
    "image_filename": "product_sizes_layouts_sets/3_v3.png",
    "is_listed": 1
  },
  {
    "id": 10,
    "product_size_id": 4,
    "layout_id": 1,
    "set_id": 1,
    "image_filename": "product_sizes_layouts_sets/1_v3.png",
    "is_listed": 1
  },
  {
    "id": 12,
    "product_size_id": 4,
    "layout_id": 1,
    "set_id": 3,
    "image_filename": "product_sizes_layouts_sets/3_v3.png",
    "is_listed": 1
  },
  {
    "id": 13,
    "product_size_id": 4,
    "layout_id": 1,
    "set_id": 4,
    "image_filename": "product_sizes_layouts_sets/13_v2.png",
    "is_listed": 1
  },
  {
    "id": 14,
    "product_size_id": 4,
    "layout_id": 1,
    "set_id": 5,
    "image_filename": "product_sizes_layouts_sets/14.png",
    "is_listed": 1
  },
  {
    "id": 4,
    "product_size_id": 2,
    "layout_id": 1,
    "set_id": 1,
    "image_filename": "product_sizes_layouts_sets/8x12-2020-engage.png",
    "is_listed": 1
  },
  {
    "id": 5,
    "product_size_id": 2,
    "layout_id": 1,
    "set_id": 2,
    "image_filename": "product_sizes_layouts_sets/8x12-2020-flow.png",
    "is_listed": 1
  },
  {
    "id": 6,
    "product_size_id": 2,
    "layout_id": 1,
    "set_id": 3,
    "image_filename": "product_sizes_layouts_sets/8x12-2020-power.png",
    "is_listed": 1
  },
  {
    "id": 7,
    "product_size_id": 3,
    "layout_id": 1,
    "set_id": 1,
    "image_filename": "product_sizes_layouts_sets/8x10-2020-engage.png",
    "is_listed": 1
  },
  {
    "id": 8,
    "product_size_id": 3,
    "layout_id": 1,
    "set_id": 2,
    "image_filename": "product_sizes_layouts_sets/8x10-2020-flow.png",
    "is_listed": 1
  },
  {
    "id": 9,
    "product_size_id": 3,
    "layout_id": 1,
    "set_id": 3,
    "image_filename": "product_sizes_layouts_sets/8x10-2020-power.png",
    "is_listed": 1
  },
  {
    "id": 16,
    "product_size_id": 5,
    "layout_id": 1,
    "set_id": 1,
    "image_filename": "product_sizes_layouts_sets/8x12-2020-engage.png",
    "is_listed": 1
  },
  {
    "id": 17,
    "product_size_id": 5,
    "layout_id": 1,
    "set_id": 2,
    "image_filename": "product_sizes_layouts_sets/8x12-2020-flow.png",
    "is_listed": 1
  },
  {
    "id": 18,
    "product_size_id": 5,
    "layout_id": 1,
    "set_id": 3,
    "image_filename": "product_sizes_layouts_sets/8x12-2020-power.png",
    "is_listed": 1
  },
  {
    "id": 19,
    "product_size_id": 5,
    "layout_id": 1,
    "set_id": 4,
    "image_filename": "product_sizes_layouts_sets/8x12-2020-gradient.png",
    "is_listed": 1
  },
  {
    "id": 21,
    "product_size_id": 6,
    "layout_id": 1,
    "set_id": 1,
    "image_filename": "product_sizes_layouts_sets/8x10-2020-engage.png",
    "is_listed": 1
  },
  {
    "id": 22,
    "product_size_id": 6,
    "layout_id": 1,
    "set_id": 2,
    "image_filename": "product_sizes_layouts_sets/8x10-2020-flow.png",
    "is_listed": 1
  },
  {
    "id": 23,
    "product_size_id": 6,
    "layout_id": 1,
    "set_id": 3,
    "image_filename": "product_sizes_layouts_sets/8x10-2020-power.png",
    "is_listed": 1
  },
  {
    "id": 24,
    "product_size_id": 6,
    "layout_id": 1,
    "set_id": 4,
    "image_filename": "product_sizes_layouts_sets/8x10-2020-gradient.png",
    "is_listed": 1
  },
  {
    "id": 2,
    "product_size_id": 1,
    "layout_id": 1,
    "set_id": 2,
    "image_filename": "product_sizes_layouts_sets/12x12-2020-flow.png",
    "is_listed": 1
  },
  {
    "id": 11,
    "product_size_id": 4,
    "layout_id": 1,
    "set_id": 2,
    "image_filename": "product_sizes_layouts_sets/12x12-2020-flow.png",
    "is_listed": 1
  },
  {
    "id": 15,
    "product_size_id": 4,
    "layout_id": 1,
    "set_id": 6,
    "image_filename": "product_sizes_layouts_sets/12x12-2020-tweeners-v2.png",
    "is_listed": 1
  },
  {
    "id": 20,
    "product_size_id": 5,
    "layout_id": 1,
    "set_id": 6,
    "image_filename": "product_sizes_layouts_sets/8x12-2020-tweeners-v2.png",
    "is_listed": 1
  },
  {
    "id": 25,
    "product_size_id": 6,
    "layout_id": 1,
    "set_id": 6,
    "image_filename": "product_sizes_layouts_sets/8x10-2020-tweeners-v2.png",
    "is_listed": 1
  }
]
